bottlenest/__init__.py
bottlenest/__main__.py
bottlenest/common/Injectable.py
bottlenest/common/__init__.py
bottlenest/config/ConfigModule.py
bottlenest/config/ConfigService.py
bottlenest/config/__init__.py
bottlenest/core/NestApplicationContext.py
bottlenest/core/NestFactory.py
bottlenest/core/NestLogger.py
bottlenest/core/NestMethodDecorator.py
bottlenest/core/NestModule.py
bottlenest/core/NestModuleContext.py
bottlenest/core/NestProvider.py
bottlenest/core/NestTransport.py
bottlenest/corecommands/BuildCoreCommand.py
bottlenest/corecommands/NewCoreCommand.py
bottlenest/http.py
bottlenest/metaClasses/NestProvider.py
bottlenest/metaClasses/NestProviderContext.py
bottlenest/metaClasses/Singleton.py
bottlenest/templates/__init__.py
bottlenest/templates/helloworld/README.md
bottlenest/templates/helloworld/pyproject.toml
bottlenest/templates/helloworld/src/myapi/__init__.py
bottlenest/templates/helloworld/src/myapi/app/AppController.py
bottlenest/templates/helloworld/src/myapi/app/AppModule.py
bottlenest/templates/helloworld/src/myapi/app/AppService.py
bottlenest/templates/helloworld/src/myapi/main.py
bottlenest/templates/helloworld/tests/__init__.py
bottlenest/transports/InputTransportsFactory.py
bottlenest/transports/cli/CliTransport.py
bottlenest/transports/cli/CommandFactory.py
bottlenest/transports/cli/__init__.py
bottlenest/transports/cli/decorators/NestCommand.py
bottlenest/transports/cli/decorators/NestCommandArgument.py
bottlenest/transports/cli/decorators/__init__.py
bottlenest/transports/http/HttpTransport.py
bottlenest/transports/http/NestHttpModule.py
bottlenest/transports/http/__init__.py
bottlenest/transports/http/decorators/NestBody.py
bottlenest/transports/http/decorators/NestController.py
bottlenest/transports/http/decorators/NestRoute.py
bottlenest/transports/http/decorators/__init__.py
bottlenest/transports/http/errors/BadRequestError.py
bottlenest/transports/http/errors/HttpError.py
bottlenest/transports/http/errors/__init__.py
bottlenest-0.0.20.dist-info/LICENSE
bottlenest-0.0.20.dist-info/METADATA
bottlenest-0.0.20.dist-info/WHEEL
bottlenest-0.0.20.dist-info/entry_points.txt
bottlenest-0.0.20.dist-info/RECORD
