Metadata-Version: 2.1
Name: bottlenest
Version: 0.0.20
Summary: A small example package
Home-page: https://github.com/giovannefeitosa/bottlenest
License: MIT
Keywords: example
Author: Giovanne Feitosa Afonso
Author-email: giovanneafonso@gmail.com
Requires-Python: >=3.10,<4
Classifier: License :: OSI Approved :: MIT License
Classifier: Programming Language :: Python :: 3
Classifier: Programming Language :: Python :: 3.10
Classifier: Programming Language :: Python :: 3.11
Requires-Dist: asyncio (>=3.4.3,<4.0.0)
Requires-Dist: eventlet (>=0.33.3,<0.34.0)
Requires-Dist: flask (>=2.2.3,<3.0.0)
Requires-Dist: inquirer (>=3.1.3,<4.0.0)
Requires-Dist: python-dotenv (>=1.0.0,<2.0.0)
Requires-Dist: python-socketio (>=5.8.0,<6.0.0)
Requires-Dist: requests (>=2.28.2,<3.0.0)
Project-URL: Repository, https://github.com/giovannefeitosa/bottlenest
